quipu_sdk/__init__.py
quipu_sdk/client.py
quipu_sdk/proxy.py
quipu_sdk/py.typed
quipu_sdk/schemas.py
quipu_sdk/utils.py
quipu_sdk-0.1.1.dist-info/METADATA
quipu_sdk-0.1.1.dist-info/WHEEL
quipu_sdk-0.1.1.dist-info/RECORD
