Metadata-Version: 2.1
Name: quipu-sdk
Version: 0.1.1
Summary: 
Author: obahamonde
Author-email: oscarmartinbahamondemunoz@gmail.com
Requires-Python: >=3.10,<4.0
Classifier: Programming Language :: Python :: 3
Classifier: Programming Language :: Python :: 3.10
Classifier: Programming Language :: Python :: 3.11
Classifier: Programming Language :: Python :: 3.12
Requires-Dist: httpx (>=0.27.0,<0.28.0)
Requires-Dist: pydantic (>=2.7.3,<3.0.0)
